colacorn/__init__.py
colacorn/pipeline.py
colacorn-0.7.0.dist-info/LICENSE
colacorn-0.7.0.dist-info/METADATA
colacorn-0.7.0.dist-info/WHEEL
colacorn-0.7.0.dist-info/top_level.txt
colacorn-0.7.0.dist-info/RECORD
